new_print_lib/__init__.py
new_print_lib/format.py
new_print_lib/nprint.py
new_print_lib/colors/__init__.py
new_print_lib/colors/colors.py
new_print_lib/colors/shades/__init__.py
new_print_lib/colors/shades/blues.py
new_print_lib/colors/shades/browns.py
new_print_lib/colors/shades/greens.py
new_print_lib/colors/shades/greys.py
new_print_lib/colors/shades/oranges.py
new_print_lib/colors/shades/pinks.py
new_print_lib/colors/shades/purples.py
new_print_lib/colors/shades/reds.py
new_print_lib/colors/shades/whites.py
new_print_lib/colors/shades/yellows.py
new_print_lib/font_styles/__init__.py
new_print_lib/font_styles/font_styles.py
new_print_lib/literals/__init__.py
new_print_lib/literals/colors.py
new_print_lib/literals/font_styles.py
new_print_lib-1.0.2.dist-info/LICENSE
new_print_lib-1.0.2.dist-info/METADATA
new_print_lib-1.0.2.dist-info/WHEEL
new_print_lib-1.0.2.dist-info/top_level.txt
new_print_lib-1.0.2.dist-info/RECORD
